discord_components/__init__.py
discord_components/client.py
discord_components/component.py
discord_components/const.py
discord_components/dpy_overrides.py
discord_components/http.py
discord_components/interaction.py
discord_components/paginator.py
discord_components/utils.py
discord_components/ext/filters.py
xphn_discord_components-1.1.dist-info/LICENSE
xphn_discord_components-1.1.dist-info/METADATA
xphn_discord_components-1.1.dist-info/WHEEL
xphn_discord_components-1.1.dist-info/top_level.txt
xphn_discord_components-1.1.dist-info/RECORD
